README.rst
setup.py
familysearch/__init__.py
familysearch/authentication.py
familysearch/authorities.py
familysearch/changeHistory.py
familysearch/discovery.py
familysearch/discussions.py
familysearch/memories.py
familysearch/ordinances.py
familysearch/parentsAndChildren.py
familysearch/pedigree.py
familysearch/person.py
familysearch/places.py
familysearch/records.py
familysearch/searchAndMatch.py
familysearch/sources.py
familysearch/spouses.py
familysearch/user.py
familysearch/utilities.py
familysearch/vocabularies.py
familysearch_python_sdk_opensource.egg-info/PKG-INFO
familysearch_python_sdk_opensource.egg-info/SOURCES.txt
familysearch_python_sdk_opensource.egg-info/dependency_links.txt
familysearch_python_sdk_opensource.egg-info/top_level.txt
test/test_basefs.py
test/test_enhanced_request.py