Metadata-Version: 1.1
Name: familysearch-python-sdk-opensource
Version: 1.2.0
Summary: A Python SDK for FamilySearch.org
Home-page: https://github.com/elderamevans/familysearch-python-sdk-opensource
Author: Elder Evans
Author-email: elderamevans@gmail.com
License: UNKNOWN
Download-URL: https://github.com/elderamevans/familysearch-python-sdk-opensource/releases/tag/v1.2.0
Keywords: FamilySearch,API,REST,family history,geneaolgy,JSON
Platform: UNKNOWN
Classifier: Development Status :: 5 - Production/Stable
Classifier: Environment :: Console
Classifier: Environment :: MacOS X
Classifier: Environment :: Web Environment
Classifier: Environment :: Win32 (MS Windows)
Classifier: Environment :: X11 Applications
Classifier: License :: OSI Approved :: BSD License
Classifier: Operating System :: OS Independent
Classifier: Programming Language :: Python :: 2
Classifier: Programming Language :: Python :: 2.6
Classifier: Programming Language :: Python :: 2.7
Classifier: Programming Language :: Python :: 3
Classifier: Programming Language :: Python :: 3.2
Classifier: Programming Language :: Python :: 3.3
Classifier: Programming Language :: Python :: 3.4
Classifier: Topic :: Internet :: WWW/HTTP
Classifier: Topic :: Sociology :: Genealogy
Classifier: Topic :: Software Development :: Libraries :: Python Modules
